applicable/__init__.py
applicable-1.1.1.dist-info/METADATA
applicable-1.1.1.dist-info/WHEEL
applicable-1.1.1.dist-info/top_level.txt
applicable-1.1.1.dist-info/RECORD
