Metadata-Version: 2.1
Name: applicable
Version: 1.1.1
Summary: Test callables without raising exceptions
Home-page: https://github.com/JediChamp178/applicable
Author: Finn Mason
License: GNU General Public License
Platform: UNKNOWN
Classifier: License :: Free for non-commercial use
Classifier: Development Status :: 5 - Production/Stable
Classifier: Programming Language :: Python :: 3
Classifier: Programming Language :: Python :: 3.6
Classifier: Programming Language :: Python :: 3.7
Classifier: Programming Language :: Python :: 3.8
Classifier: Programming Language :: Python :: 3.9
Classifier: Programming Language :: Python :: 3.10
